src/__init__.py
src/boolean_to_signed.py
boolean_to_signed-1.0.1.dist-info/LICENSE.txt
boolean_to_signed-1.0.1.dist-info/METADATA
boolean_to_signed-1.0.1.dist-info/WHEEL
boolean_to_signed-1.0.1.dist-info/top_level.txt
boolean_to_signed-1.0.1.dist-info/RECORD
