Metadata-Version: 2.1
Name: boolean-to-signed
Version: 1.0.1
Summary: Returns -1 if input is false, or 1 if input is true.
Home-page: UNKNOWN
Author: Najim Islam
License: UNKNOWN
Keywords: boolean,signed,convert,sign,conversion
Platform: UNKNOWN
